{
  "format": "svg-enhanced",
  "metadata": {
    "templateId": "template-115m2-3br-split-004",
    "projectName": "3BR Split-Level 115m²",
    "location": "Denmark",
    "buildingCode": "BR18/BR23",
    "totalArea": 115,
    "buildingType": "house",
    "description": "3-bedroom with split zoning separating private and public areas",
    "tags": [
      "3BR",
      "split-level",
      "zoning",
      "privacy",
      "family"
    ],
    "compliant": true
  },
  "exterior": {
    "path": "M 0,0 L 14,0 L 14,8.5 L 0,8.5 Z",
    "thickness": 0.3,
    "material": "brick"
  },
  "divisions": [
    {
      "id": "div-1",
      "path": "M 4.5,0 L 4.5,8.5",
      "thickness": 0.12,
      "connects": [
        "exterior",
        "exterior"
      ],
      "material": "gypsum-board",
      "structural": false
    },
    {
      "id": "div-2",
      "path": "M 9,0 L 9,8.5",
      "thickness": 0.12,
      "connects": [
        "exterior",
        "exterior"
      ],
      "material": "gypsum-board",
      "structural": false
    },
    {
      "id": "div-3",
      "path": "M 4.5,5.5 L 9,5.5",
      "thickness": 0.12,
      "connects": [
        "div-1",
        "div-2"
      ],
      "material": "gypsum-board",
      "structural": false
    },
    {
      "id": "div-4",
      "path": "M 9,2.5 L 14,2.5",
      "thickness": 0.12,
      "connects": [
        "div-2",
        "exterior"
      ],
      "material": "gypsum-board",
      "structural": false
    },
    {
      "id": "div-5",
      "path": "M 9,5.5 L 14,5.5",
      "thickness": 0.12,
      "connects": [
        "div-2",
        "exterior"
      ],
      "material": "gypsum-board",
      "structural": false
    },
    {
      "id": "div-6",
      "path": "M 11.5,5.5 L 11.5,8.5",
      "thickness": 0.12,
      "connects": [
        "div-5",
        "exterior"
      ],
      "material": "gypsum-board",
      "structural": false
    }
  ],
  "rooms": [
    {
      "id": "room-living",
      "name": "Living Room",
      "type": "Living Room",
      "boundary": "M 0,0 L 4.5,0 L 4.5,8.5 L 0,8.5 Z",
      "area": 38.25,
      "features": [
        "window:w-1",
        "window:w-2",
        "window:w-3",
        "door:d-1"
      ],
      "compliance": []
    },
    {
      "id": "room-dining",
      "name": "Dining Room",
      "type": "Dining Room",
      "boundary": "M 4.5,0 L 9,0 L 9,5.5 L 4.5,5.5 Z",
      "area": 24.75,
      "features": [
        "window:w-4",
        "door:d-2"
      ],
      "compliance": []
    },
    {
      "id": "room-kitchen",
      "name": "Kitchen",
      "type": "Kitchen",
      "boundary": "M 4.5,5.5 L 9,5.5 L 9,8.5 L 4.5,8.5 Z",
      "area": 13.5,
      "features": [
        "door:d-3"
      ],
      "compliance": []
    },
    {
      "id": "room-bedroom1",
      "name": "Master Bedroom",
      "type": "Bedroom",
      "boundary": "M 9,0 L 14,0 L 14,2.5 L 9,2.5 Z",
      "area": 12.5,
      "features": [
        "window:w-5",
        "door:d-4"
      ],
      "compliance": []
    },
    {
      "id": "room-bedroom2",
      "name": "Bedroom 2",
      "type": "Bedroom",
      "boundary": "M 9,2.5 L 14,2.5 L 14,5.5 L 9,5.5 Z",
      "area": 15,
      "features": [
        "window:w-6",
        "door:d-5"
      ],
      "compliance": []
    },
    {
      "id": "room-bedroom3",
      "name": "Bedroom 3",
      "type": "Bedroom",
      "boundary": "M 9,5.5 L 11.5,5.5 L 11.5,8.5 L 9,8.5 Z",
      "area": 7.5,
      "features": [
        "door:d-6"
      ],
      "compliance": []
    },
    {
      "id": "room-bathroom",
      "name": "Bathroom",
      "type": "Bathroom",
      "boundary": "M 11.5,5.5 L 14,5.5 L 14,8.5 L 11.5,8.5 Z",
      "area": 7.5,
      "features": [
        "window:w-7",
        "door:d-7"
      ],
      "compliance": []
    }
  ],
  "openings": [
    {
      "id": "d-1",
      "type": "door",
      "onPath": "exterior",
      "atPosition": 0.06,
      "width": 1,
      "swing": "left"
    },
    {
      "id": "d-2",
      "type": "door",
      "onPath": "div-1",
      "atPosition": 0.35,
      "width": 0.9,
      "swing": "right"
    },
    {
      "id": "d-3",
      "type": "door",
      "onPath": "div-3",
      "atPosition": 0.5,
      "width": 0.9,
      "swing": "right"
    },
    {
      "id": "d-4",
      "type": "door",
      "onPath": "div-2",
      "atPosition": 0.15,
      "width": 0.9,
      "swing": "left"
    },
    {
      "id": "d-5",
      "type": "door",
      "onPath": "div-2",
      "atPosition": 0.47,
      "width": 0.9,
      "swing": "left"
    },
    {
      "id": "d-6",
      "type": "door",
      "onPath": "div-5",
      "atPosition": 0.25,
      "width": 0.9,
      "swing": "left"
    },
    {
      "id": "d-7",
      "type": "door",
      "onPath": "div-6",
      "atPosition": 0.5,
      "width": 0.9,
      "swing": "none"
    },
    {
      "id": "w-1",
      "type": "window",
      "onPath": "exterior",
      "atPosition": 0.12,
      "width": 2
    },
    {
      "id": "w-2",
      "type": "window",
      "onPath": "exterior",
      "atPosition": 0.25,
      "width": 1.5
    },
    {
      "id": "w-3",
      "type": "window",
      "onPath": "exterior",
      "atPosition": 0.85,
      "width": 1.5
    },
    {
      "id": "w-4",
      "type": "window",
      "onPath": "exterior",
      "atPosition": 0.35,
      "width": 1.8
    },
    {
      "id": "w-5",
      "type": "window",
      "onPath": "exterior",
      "atPosition": 0.78,
      "width": 1.5
    },
    {
      "id": "w-6",
      "type": "window",
      "onPath": "exterior",
      "atPosition": 0.48,
      "width": 1.5
    },
    {
      "id": "w-7",
      "type": "window",
      "onPath": "exterior",
      "atPosition": 0.95,
      "width": 1
    }
  ]
}
